setup.py
chlocust/__init__.py
chlocust/client.py
chlocust/locust.py
chlocust/types.py
chlocust.egg-info/PKG-INFO
chlocust.egg-info/SOURCES.txt
chlocust.egg-info/dependency_links.txt
chlocust.egg-info/requires.txt
chlocust.egg-info/top_level.txt
chlocust.egg-info/zip-safe