Metadata-Version: 1.1
Name: chlocust
Version: 0.1.5
Summary: Locust plugin for ClickHouse load testing
Home-page: https://github.com/kotyakov/chlocust
Author: Maxim Kotyakov
Author-email: m.a.kotyakov@yandex.ru
License: UNKNOWN
Platform: UNKNOWN
Classifier: Development Status :: 4 - Beta
Classifier: License :: OSI Approved :: MIT License
Classifier: Operating System :: OS Independent
Classifier: Programming Language :: Python
Classifier: Programming Language :: Python :: 3
Classifier: Programming Language :: Python :: 3.5
Classifier: Programming Language :: Python :: 3.6
Classifier: Programming Language :: Python :: 3.7
Classifier: Programming Language :: Python :: 3.8
Classifier: Topic :: Software Development :: Libraries :: Python Modules
